py65emu/__init__.py
py65emu/cpu.py
py65emu/debug.py
py65emu/mmu.py
py65emu/operation.py
py65emu-0.1.0.dist-info/AUTHORS.rst
py65emu-0.1.0.dist-info/LICENSE
py65emu-0.1.0.dist-info/METADATA
py65emu-0.1.0.dist-info/WHEEL
py65emu-0.1.0.dist-info/top_level.txt
py65emu-0.1.0.dist-info/RECORD
